dailylog/__init__.py
dailylog/log_handler.py
dailylog-0.0.4.dist-info/LICENSE
dailylog-0.0.4.dist-info/METADATA
dailylog-0.0.4.dist-info/WHEEL
dailylog-0.0.4.dist-info/top_level.txt
dailylog-0.0.4.dist-info/RECORD
