Metadata-Version: 2.1
Name: dailylog
Version: 0.0.4
Summary: record logs per day
Home-page: https://github.com/darkwhale/dailylog
Author: xinyang zhou
Author-email: 308885823@qq.com
License: UNKNOWN
Download-URL: https://github.com/darkwhale/dailylog/archive/master.zip
Keywords: log,day
Platform: UNKNOWN
Classifier: Development Status :: 4 - Beta
Classifier: Operating System :: OS Independent
Classifier: Intended Audience :: Developers
Classifier: License :: OSI Approved :: BSD License
Classifier: Programming Language :: Python
Classifier: Programming Language :: Python :: Implementation
Classifier: Programming Language :: Python :: 2
Classifier: Programming Language :: Python :: 2.7
Classifier: Programming Language :: Python :: 3
Classifier: Programming Language :: Python :: 3.4
Classifier: Programming Language :: Python :: 3.5
Classifier: Programming Language :: Python :: 3.6
Classifier: Topic :: Software Development :: Libraries
